google/ads/admanager/__init__.py
google/ads/admanager/gapic_version.py
google/ads/admanager/py.typed
google/ads/admanager_v1/__init__.py
google/ads/admanager_v1/gapic_metadata.json
google/ads/admanager_v1/gapic_version.py
google/ads/admanager_v1/py.typed
google/ads/admanager_v1/services/__init__.py
google/ads/admanager_v1/services/ad_break_service/__init__.py
google/ads/admanager_v1/services/ad_break_service/client.py
google/ads/admanager_v1/services/ad_break_service/pagers.py
google/ads/admanager_v1/services/ad_break_service/transports/__init__.py
google/ads/admanager_v1/services/ad_break_service/transports/base.py
google/ads/admanager_v1/services/ad_break_service/transports/rest.py
google/ads/admanager_v1/services/ad_break_service/transports/rest_base.py
google/ads/admanager_v1/services/ad_review_center_ad_service/__init__.py
google/ads/admanager_v1/services/ad_review_center_ad_service/client.py
google/ads/admanager_v1/services/ad_review_center_ad_service/pagers.py
google/ads/admanager_v1/services/ad_review_center_ad_service/transports/__init__.py
google/ads/admanager_v1/services/ad_review_center_ad_service/transports/base.py
google/ads/admanager_v1/services/ad_review_center_ad_service/transports/rest.py
google/ads/admanager_v1/services/ad_review_center_ad_service/transports/rest_base.py
google/ads/admanager_v1/services/ad_unit_service/__init__.py
google/ads/admanager_v1/services/ad_unit_service/client.py
google/ads/admanager_v1/services/ad_unit_service/pagers.py
google/ads/admanager_v1/services/ad_unit_service/transports/__init__.py
google/ads/admanager_v1/services/ad_unit_service/transports/base.py
google/ads/admanager_v1/services/ad_unit_service/transports/rest.py
google/ads/admanager_v1/services/ad_unit_service/transports/rest_base.py
google/ads/admanager_v1/services/application_service/__init__.py
google/ads/admanager_v1/services/application_service/client.py
google/ads/admanager_v1/services/application_service/pagers.py
google_ads_admanager-0.8.0.dist-info/licenses/LICENSE
google_ads_admanager-0.8.0.dist-info/METADATA
google_ads_admanager-0.8.0.dist-info/WHEEL
google_ads_admanager-0.8.0.dist-info/top_level.txt
google_ads_admanager-0.8.0.dist-info/RECORD
